modulr/__init__.py
modulr/add_docstring.py
modulr/make_module.py
modulr-0.0.2.dist-info/LICENSE.txt
modulr-0.0.2.dist-info/METADATA
modulr-0.0.2.dist-info/WHEEL
modulr-0.0.2.dist-info/top_level.txt
modulr-0.0.2.dist-info/RECORD
