Metadata-Version: 2.1
Name: modulr
Version: 0.0.2
Summary: Save currently defined classes and functions to modules
Home-page: https://github.com/marskar/modulr
Author: Martin Skarzynski
Author-email: marskar@gmail.com
License: UNKNOWN
Platform: UNKNOWN
Classifier: Programming Language :: Python :: 3
Classifier: License :: OSI Approved :: MIT License
Classifier: Operating System :: OS Independent
